mango/__init__.py
mango/drive.py
mango/encoder.py
mango/expression.py
mango/fields.py
mango/index.py
mango/meta.py
mango/models.py
mango/py.typed
mango/result.py
mango/source.py
mango/stage.py
mango/utils.py
mango_odm-0.4.1.dist-info/METADATA
mango_odm-0.4.1.dist-info/WHEEL
mango_odm-0.4.1.dist-info/licenses/LICENSE
mango_odm-0.4.1.dist-info/RECORD
