Metadata-Version: 2.1
Name: mango-odm
Version: 0.4.1
Summary: 🥭 Async MongoDB ODM with type hints in Python
Keywords: mongo mongodb async asyncio odm types pydantic motor
Author-Email: Akirami <akiramiaya@outlook.com>
License: MIT
Classifier: Development Status :: 4 - Beta
Classifier: Framework :: AsyncIO
Classifier: Intended Audience :: Developers
Classifier: License :: OSI Approved :: MIT License
Classifier: Operating System :: OS Independent
Classifier: Programming Language :: Python
Classifier: Programming Language :: Python :: 3
Classifier: Programming Language :: Python :: 3 :: Only
Classifier: Programming Language :: Python :: 3.10
Classifier: Programming Language :: Python :: 3.11
Classifier: Programming Language :: Python :: 3.12
Classifier: Topic :: Database
Classifier: Topic :: Database :: Front-Ends
Classifier: Topic :: Software Development
Classifier: Topic :: Software Development :: Object Brokering
Classifier: Topic :: Software Development :: Libraries
Classifier: Topic :: Software Development :: Libraries :: Python Modules
Classifier: Typing :: Typed
Project-URL: Repository, https://github.com/A-kirami/mango
Requires-Python: <4.0,>=3.10
Requires-Dist: motor>=3.4.0
Requires-Dist: pydantic>=2.7.0
Requires-Dist: motor-types>=1.0.0b4
